soupsieve/__init__.py
soupsieve/__meta__.py
soupsieve/css_match.py
soupsieve/css_parser.py
soupsieve/css_types.py
soupsieve/pretty.py
soupsieve/py.typed
soupsieve/util.py
soupsieve-2.3.dist-info/LICENSE.md
soupsieve-2.3.dist-info/METADATA
soupsieve-2.3.dist-info/WHEEL
soupsieve-2.3.dist-info/top_level.txt
soupsieve-2.3.dist-info/RECORD
