Metadata-Version: 2.1
Name: soupsieve
Version: 2.3
Summary: A modern CSS selector implementation for Beautiful Soup.
Home-page: https://github.com/facelessuser/soupsieve
Author: Isaac Muse
Author-email: Isaac.Muse@gmail.com
License: MIT License
Keywords: CSS HTML XML selector filter query soup
Platform: UNKNOWN
Classifier: Development Status :: 5 - Production/Stable
Classifier: Environment :: Console
Classifier: Intended Audience :: Developers
Classifier: License :: OSI Approved :: MIT License
Classifier: Operating System :: OS Independent
Classifier: Programming Language :: Python :: 3
Classifier: Programming Language :: Python :: 3.6
Classifier: Programming Language :: Python :: 3.7
Classifier: Programming Language :: Python :: 3.8
Classifier: Programming Language :: Python :: 3.9
Classifier: Programming Language :: Python :: 3.10
Classifier: Topic :: Internet :: WWW/HTTP :: Dynamic Content
Classifier: Topic :: Software Development :: Libraries :: Python Modules
Classifier: Typing :: Typed
Requires-Python: >=3.6
License-File: LICENSE.md
